README.md
setup.cfg
setup.py
dsd_aali/Binomialdistribution.py
dsd_aali/Gaussiandistribution.py
dsd_aali/Generaldistribution.py
dsd_aali/__init__.py
dsd_aali.egg-info/PKG-INFO
dsd_aali.egg-info/SOURCES.txt
dsd_aali.egg-info/dependency_links.txt
dsd_aali.egg-info/not-zip-safe
dsd_aali.egg-info/top_level.txt